sense_file/__init__.py
sense_file/decorate.py
sense_file/load_file.py
sense_file/s3_file.py
sense_file-0.0.15.dist-info/METADATA
sense_file-0.0.15.dist-info/WHEEL
sense_file-0.0.15.dist-info/top_level.txt
sense_file-0.0.15.dist-info/RECORD
