Metadata-Version: 2.1
Name: sense-file
Version: 0.0.15
Summary: sense file
Home-page: https://upload.pypi.org/legacy/
Author: liuguangbin
Author-email: liuguangbin@sensedeal.ai
License: BSD License
Platform: UNKNOWN
Classifier: Environment :: Web Environment
Classifier: Intended Audience :: Developers
Classifier: License :: OSI Approved :: BSD License
Classifier: Operating System :: OS Independent
Classifier: Programming Language :: Python
Classifier: Programming Language :: Python :: 3.6
Classifier: Topic :: Internet :: WWW/HTTP
Requires-Dist: boto3
Requires-Dist: sense-core (>=0.2.82)
